hidcd.py
posiflex_hidcd-1.0.0.dist-info/LICENSE
posiflex_hidcd-1.0.0.dist-info/METADATA
posiflex_hidcd-1.0.0.dist-info/WHEEL
posiflex_hidcd-1.0.0.dist-info/top_level.txt
posiflex_hidcd-1.0.0.dist-info/RECORD
