Metadata-Version: 2.1
Name: posiflex-hidcd
Version: 1.0.0
Summary: USB HID Cash Drawer Interface
Author-email: Nathan Fraser <ndf-zz@6-v.org>
License: MIT
Project-URL: homepage, https://github.com/ndf-zz/posiflex-hidcd
Keywords: posiflex,cr-4xxx,usb,hid
Classifier: Development Status :: 3 - Alpha
Classifier: Topic :: Office/Business :: Financial :: Point-Of-Sale
Classifier: Topic :: System :: Hardware :: Universal Serial Bus (USB) :: Human Interface Device (HID)
Classifier: Operating System :: OS Independent
Classifier: Programming Language :: Python :: 3
Requires-Python: >=3.9
License-File: LICENSE
Requires-Dist: cffi
Requires-Dist: hidapi-cffi
